<?xml version="1.0" encoding="UTF-8"?>
<!DOCTYPE beans PUBLIC "-//SPRING//DTD BEAN//EN" "http://www.springframework.org/dtd/spring-beans.dtd" >
<beans>
  <!-- most phone defaults properties is set in sipxconfig.properties.in -->
  <bean id="phoneDefaults" class="org.sipfoundry.sipxconfig.device.DeviceDefaults">
    <property name="dialPlanContext" ref="dialPlanContext" />
    <property name="domainManager" ref="domainManager" />
    <property name="sipxServer" ref="sipxServer" />
  </bean>


  <bean id="profileGenerator" class="org.sipfoundry.sipxconfig.device.VelocityProfileGenerator">
    <property name="velocityEngine" ref="velocityEngine" />
  </bean>
</beans>
